{
  "dataset_dir": "02_语种工程资源/蒙古语/03_合成数据生成_20260702/VL7/10_公告通知",
  "total_images": 6,
  "passed_basic": 6,
  "failed_basic": [],
  "total_blocks": 59,
  "total_overflow_blocks": 0,
  "total_out_of_bounds_blocks": 0,
  "total_cyrillic_blocks": 0,
  "total_tibetan_small_mark_blocks": 0,
  "total_pua_blocks": 0,
  "total_unsupported_char_blocks": 0,
  "unsupported_char_counts": {},
  "total_script_residue_blocks": {
    "latin": 0,
    "cjk": 0,
    "cyrillic": 0,
    "tibetan": 0,
    "arabic": 0,
    "mongolian": 0,
    "hangul": 0
  },
  "category_summary": {
    "notice_announcement": {
      "total": 6,
      "passed_basic": 6,
      "total_blocks": 59,
      "overflow_blocks": 0,
      "out_of_bounds_blocks": 0,
      "cyrillic_blocks": 0,
      "tibetan_small_mark_blocks": 0,
      "pua_blocks": 0,
      "unsupported_char_blocks": 0,
      "script_residue_blocks": {
        "latin": 0,
        "cjk": 0,
        "cyrillic": 0,
        "tibetan": 0,
        "arabic": 0,
        "mongolian": 0,
        "hangul": 0
      }
    }
  },
  "items": [
    {
      "document_id": "10_notice_announcement_vertical_tree_01",
      "category": "notice_announcement",
      "variant": 1,
      "layout_name": "notice_announcement_vertical_tree_01",
      "image": "02_语种工程资源/蒙古语/03_合成数据生成_20260702/VL7/10_公告通知/images/10_notice_announcement_vertical_tree_01.png",
      "label": "02_语种工程资源/蒙古语/03_合成数据生成_20260702/VL7/10_公告通知/labels/10_notice_announcement_vertical_tree_01.json",
      "html": "02_语种工程资源/蒙古语/03_合成数据生成_20260702/VL7/10_公告通知/html/10_notice_announcement_vertical_tree_01.html",
      "blocks": 8,
      "overflow_blocks": 0,
      "page_width": 696,
      "page_height": 1128,
      "width": 696,
      "height": 1128,
      "nonblank_score": 32.747,
      "min_blocks_required": 5,
      "out_of_bounds_blocks": 0,
      "tiny_boxes": 0,
      "cyrillic_blocks": 0,
      "tibetan_small_mark_blocks": 0,
      "pua_blocks": 0,
      "unsupported_char_blocks": 0,
      "unsupported_char_counts": {},
      "script_residue_blocks": {
        "latin": 0,
        "cjk": 0,
        "cyrillic": 0,
        "tibetan": 0,
        "arabic": 0,
        "mongolian": 0,
        "hangul": 0
      },
      "pass_basic": true
    },
    {
      "document_id": "10_notice_announcement_vertical_tree_02",
      "category": "notice_announcement",
      "variant": 2,
      "layout_name": "notice_announcement_vertical_tree_02",
      "image": "02_语种工程资源/蒙古语/03_合成数据生成_20260702/VL7/10_公告通知/images/10_notice_announcement_vertical_tree_02.png",
      "label": "02_语种工程资源/蒙古语/03_合成数据生成_20260702/VL7/10_公告通知/labels/10_notice_announcement_vertical_tree_02.json",
      "html": "02_语种工程资源/蒙古语/03_合成数据生成_20260702/VL7/10_公告通知/html/10_notice_announcement_vertical_tree_02.html",
      "blocks": 8,
      "overflow_blocks": 0,
      "page_width": 680,
      "page_height": 1128,
      "width": 680,
      "height": 1128,
      "nonblank_score": 39.189,
      "min_blocks_required": 5,
      "out_of_bounds_blocks": 0,
      "tiny_boxes": 0,
      "cyrillic_blocks": 0,
      "tibetan_small_mark_blocks": 0,
      "pua_blocks": 0,
      "unsupported_char_blocks": 0,
      "unsupported_char_counts": {},
      "script_residue_blocks": {
        "latin": 0,
        "cjk": 0,
        "cyrillic": 0,
        "tibetan": 0,
        "arabic": 0,
        "mongolian": 0,
        "hangul": 0
      },
      "pass_basic": true
    },
    {
      "document_id": "10_notice_announcement_vertical_tree_03",
      "category": "notice_announcement",
      "variant": 3,
      "layout_name": "notice_announcement_vertical_tree_03",
      "image": "02_语种工程资源/蒙古语/03_合成数据生成_20260702/VL7/10_公告通知/images/10_notice_announcement_vertical_tree_03.png",
      "label": "02_语种工程资源/蒙古语/03_合成数据生成_20260702/VL7/10_公告通知/labels/10_notice_announcement_vertical_tree_03.json",
      "html": "02_语种工程资源/蒙古语/03_合成数据生成_20260702/VL7/10_公告通知/html/10_notice_announcement_vertical_tree_03.html",
      "blocks": 14,
      "overflow_blocks": 0,
      "page_width": 722,
      "page_height": 1128,
      "width": 722,
      "height": 1128,
      "nonblank_score": 31.257,
      "min_blocks_required": 5,
      "out_of_bounds_blocks": 0,
      "tiny_boxes": 0,
      "cyrillic_blocks": 0,
      "tibetan_small_mark_blocks": 0,
      "pua_blocks": 0,
      "unsupported_char_blocks": 0,
      "unsupported_char_counts": {},
      "script_residue_blocks": {
        "latin": 0,
        "cjk": 0,
        "cyrillic": 0,
        "tibetan": 0,
        "arabic": 0,
        "mongolian": 0,
        "hangul": 0
      },
      "pass_basic": true
    },
    {
      "document_id": "10_notice_announcement_vertical_tree_04",
      "category": "notice_announcement",
      "variant": 4,
      "layout_name": "notice_announcement_vertical_tree_04",
      "image": "02_语种工程资源/蒙古语/03_合成数据生成_20260702/VL7/10_公告通知/images/10_notice_announcement_vertical_tree_04.png",
      "label": "02_语种工程资源/蒙古语/03_合成数据生成_20260702/VL7/10_公告通知/labels/10_notice_announcement_vertical_tree_04.json",
      "html": "02_语种工程资源/蒙古语/03_合成数据生成_20260702/VL7/10_公告通知/html/10_notice_announcement_vertical_tree_04.html",
      "blocks": 13,
      "overflow_blocks": 0,
      "page_width": 701,
      "page_height": 1128,
      "width": 701,
      "height": 1128,
      "nonblank_score": 32.59,
      "min_blocks_required": 5,
      "out_of_bounds_blocks": 0,
      "tiny_boxes": 0,
      "cyrillic_blocks": 0,
      "tibetan_small_mark_blocks": 0,
      "pua_blocks": 0,
      "unsupported_char_blocks": 0,
      "unsupported_char_counts": {},
      "script_residue_blocks": {
        "latin": 0,
        "cjk": 0,
        "cyrillic": 0,
        "tibetan": 0,
        "arabic": 0,
        "mongolian": 0,
        "hangul": 0
      },
      "pass_basic": true
    },
    {
      "document_id": "10_notice_announcement_vertical_tree_05",
      "category": "notice_announcement",
      "variant": 5,
      "layout_name": "notice_announcement_vertical_tree_05",
      "image": "02_语种工程资源/蒙古语/03_合成数据生成_20260702/VL7/10_公告通知/images/10_notice_announcement_vertical_tree_05.png",
      "label": "02_语种工程资源/蒙古语/03_合成数据生成_20260702/VL7/10_公告通知/labels/10_notice_announcement_vertical_tree_05.json",
      "html": "02_语种工程资源/蒙古语/03_合成数据生成_20260702/VL7/10_公告通知/html/10_notice_announcement_vertical_tree_05.html",
      "blocks": 7,
      "overflow_blocks": 0,
      "page_width": 644,
      "page_height": 1068,
      "width": 644,
      "height": 1068,
      "nonblank_score": 31.335,
      "min_blocks_required": 5,
      "out_of_bounds_blocks": 0,
      "tiny_boxes": 0,
      "cyrillic_blocks": 0,
      "tibetan_small_mark_blocks": 0,
      "pua_blocks": 0,
      "unsupported_char_blocks": 0,
      "unsupported_char_counts": {},
      "script_residue_blocks": {
        "latin": 0,
        "cjk": 0,
        "cyrillic": 0,
        "tibetan": 0,
        "arabic": 0,
        "mongolian": 0,
        "hangul": 0
      },
      "pass_basic": true
    },
    {
      "document_id": "10_notice_announcement_vertical_tree_06",
      "category": "notice_announcement",
      "variant": 6,
      "layout_name": "notice_announcement_vertical_tree_06",
      "image": "02_语种工程资源/蒙古语/03_合成数据生成_20260702/VL7/10_公告通知/images/10_notice_announcement_vertical_tree_06.png",
      "label": "02_语种工程资源/蒙古语/03_合成数据生成_20260702/VL7/10_公告通知/labels/10_notice_announcement_vertical_tree_06.json",
      "html": "02_语种工程资源/蒙古语/03_合成数据生成_20260702/VL7/10_公告通知/html/10_notice_announcement_vertical_tree_06.html",
      "blocks": 9,
      "overflow_blocks": 0,
      "page_width": 750,
      "page_height": 1128,
      "width": 750,
      "height": 1128,
      "nonblank_score": 35.041,
      "min_blocks_required": 5,
      "out_of_bounds_blocks": 0,
      "tiny_boxes": 0,
      "cyrillic_blocks": 0,
      "tibetan_small_mark_blocks": 0,
      "pua_blocks": 0,
      "unsupported_char_blocks": 0,
      "unsupported_char_counts": {},
      "script_residue_blocks": {
        "latin": 0,
        "cjk": 0,
        "cyrillic": 0,
        "tibetan": 0,
        "arabic": 0,
        "mongolian": 0,
        "hangul": 0
      },
      "pass_basic": true
    }
  ]
}